pyzbar/__init__.py
pyzbar/locations.py
pyzbar/pyzbar.py
pyzbar/pyzbar_error.py
pyzbar/wrapper.py
pyzbar/zbar_library.py
pyzbar/scripts/__init__.py
pyzbar/scripts/read_zbar.py
pyzbar/tests/__init__.py
pyzbar/tests/test_locations.py
pyzbar/tests/test_pyzbar.py
pyzbar/tests/test_read_zbar.py
pyzbar/tests/test_zbar_library.py
pyzbar_upright-0.1.8.data/scripts/read_zbar.py
pyzbar_upright-0.1.8.dist-info/LICENSE.txt
pyzbar_upright-0.1.8.dist-info/METADATA
pyzbar_upright-0.1.8.dist-info/WHEEL
pyzbar_upright-0.1.8.dist-info/entry_points.txt
pyzbar_upright-0.1.8.dist-info/top_level.txt
pyzbar_upright-0.1.8.dist-info/RECORD
